aw_watcher_netstatus/__init__.py
aw_watcher_netstatus/config.py
aw_watcher_netstatus/settings.py
aw_watcher_netstatus/watcher.py
aw_watcher_netstatus-1.0.1.dist-info/LICENSE
aw_watcher_netstatus-1.0.1.dist-info/WHEEL
aw_watcher_netstatus-1.0.1.dist-info/entry_points.txt
aw_watcher_netstatus-1.0.1.dist-info/METADATA
aw_watcher_netstatus-1.0.1.dist-info/RECORD
