Metadata-Version: 2.1
Name: aw-watcher-netstatus
Version: 1.0.1
Summary: An ActivityWatch monitor for observing the network connection status.
Home-page: https://github.com/sameersismail/aw-watcher-netstatus
License: MIT
Author: Sameer Ismail
Requires-Python: >=3.10,<4.0
Classifier: License :: OSI Approved :: MIT License
Classifier: Programming Language :: Python :: 3
Classifier: Programming Language :: Python :: 3.10
Classifier: Programming Language :: Python :: 3.11
Requires-Dist: aw-client (>=0.5.11,<0.6.0)
Requires-Dist: aw-core (>=0.5.11,<0.6.0)
Project-URL: Documentation, https://github.com/sameersismail/aw-watcher-netstatus
Project-URL: Repository, https://github.com/sameersismail/aw-watcher-netstatus
